stock_screener.py
stock_market_screener-0.1.2.dist-info/licenses/LICENSE
stock_market_screener-0.1.2.dist-info/METADATA
stock_market_screener-0.1.2.dist-info/WHEEL
stock_market_screener-0.1.2.dist-info/entry_points.txt
stock_market_screener-0.1.2.dist-info/top_level.txt
stock_market_screener-0.1.2.dist-info/RECORD
