Metadata-Version: 2.4
Name: stock-market-screener
Version: 0.1.2
Summary: A data-driven stock screener that analyzes Dow 30 stocks using technical indicators
Author-email: Sophie Zhang <sophieszhang.ssz@gmail.com>
License: MIT
Project-URL: Repository, https://github.com/Sophie-S-Z/Stonks.git
Project-URL: Documentation, https://github.com/Sophie-S-Z/Stonks/blob/main/README.md
Keywords: stock-screener,technical-analysis,trading,finance
Classifier: Development Status :: 3 - Alpha
Classifier: Intended Audience :: Financial and Insurance Industry
Classifier: License :: OSI Approved :: MIT License
Classifier: Programming Language :: Python :: 3
Classifier: Programming Language :: Python :: 3.8
Classifier: Programming Language :: Python :: 3.9
Classifier: Programming Language :: Python :: 3.10
Classifier: Programming Language :: Python :: 3.11
Requires-Python: >=3.8
License-File: LICENSE
Requires-Dist: pandas>=1.3.0
Requires-Dist: numpy>=1.21.0
Requires-Dist: yfinance>=0.2.0
Requires-Dist: TA-Lib>=0.4.24
Requires-Dist: matplotlib>=3.5.0
Requires-Dist: seaborn>=0.11.0
Dynamic: license-file
